objetto/__init__.py
objetto/_applications.py
objetto/_changes.py
objetto/_constants.py
objetto/_deserializers.py
objetto/_exceptions.py
objetto/_factories.py
objetto/_history.py
objetto/_observers.py
objetto/_reactions.py
objetto/_serializers.py
objetto/applications.py
objetto/applications.pyi
objetto/bases.py
objetto/changes.py
objetto/constants.py
objetto/data.py
objetto/data.pyi
objetto/deserializers.py
objetto/exceptions.py
objetto/factories.py
objetto/history.py
objetto/objects.py
objetto/objects.pyi
objetto/observers.py
objetto/py.typed
objetto/reactions.py
objetto/serializers.py
objetto/states.py
objetto/_bases/__init__.py
objetto/_bases/bases.py
objetto/_bases/dict.py
objetto/_bases/list.py
objetto/_bases/set.py
objetto/_data/__init__.py
objetto/_data/bases.py
objetto/_data/data.py
objetto/_data/dict.py
objetto/_data/list.py
objetto/_data/set.py
objetto/_objects/__init__.py
objetto/_objects/bases.py
objetto/_objects/dict.py
objetto/_objects/list.py
objetto/_objects/object.py
objetto/_objects/set.py
objetto/_states/__init__.py
objetto/_states/bases.py
objetto/_states/dict.py
objetto/_states/list.py
objetto/_states/set.py
objetto/_structures/__init__.py
objetto/_structures/bases.py
objetto/_structures/dict.py
objetto/_structures/list.py
objetto/_structures/set.py
objetto/_structures/structure.py
objetto/utils/__init__.py
objetto/utils/caller_module.py
objetto/utils/custom_repr.py
objetto/utils/dummy_context.py
objetto/utils/factoring.py
objetto/utils/lazy_import.py
objetto/utils/list_operations.py
objetto/utils/qualname.py
objetto/utils/recursive_repr.py
objetto/utils/reraise_context.py
objetto/utils/simplify_exceptions.py
objetto/utils/storage.py
objetto/utils/subject_observer.py
objetto/utils/type_checking.py
objetto/utils/weak_reference.py
objetto-1.29.2.dist-info/LICENSE
objetto-1.29.2.dist-info/METADATA
objetto-1.29.2.dist-info/WHEEL
objetto-1.29.2.dist-info/top_level.txt
objetto-1.29.2.dist-info/RECORD
