Metadata-Version: 2.1
Name: objetto
Version: 1.29.2
Summary: Object-oriented framework for building smart applications and APIs
Home-page: https://github.com/brunonicko/objetto
Author: Bruno Nicko
Author-email: brunonicko@gmail.com
License: UNKNOWN
Platform: UNKNOWN
Classifier: Intended Audience :: Developers
Classifier: License :: OSI Approved :: MIT License
Classifier: Operating System :: OS Independent
Classifier: Programming Language :: Python :: 2.7
Classifier: Programming Language :: Python :: 3.5
Classifier: Programming Language :: Python :: 3.6
Classifier: Programming Language :: Python :: 3.7
Classifier: Programming Language :: Python :: 3.8
Classifier: Programming Language :: Python :: 3.9
Classifier: Programming Language :: Python :: 3.10
Classifier: Programming Language :: Python :: Implementation :: PyPy
Requires-Python: >=2.7
Requires-Dist: pyrsistent
Requires-Dist: six
Requires-Dist: slotted (<2)
Requires-Dist: enum34 ; python_version < "3.4"
Requires-Dist: typing ; python_version < "3.5"
